EasyLoggerAJM/__init__.py
EasyLoggerAJM/_version.py
EasyLoggerAJM/custom_loggers.py
EasyLoggerAJM/easy_logger.py
EasyLoggerAJM/UncaughtExceptionHook/__init__.py
EasyLoggerAJM/UncaughtExceptionHook/filters.py
EasyLoggerAJM/UncaughtExceptionHook/uncaught_exception_hook.py
EasyLoggerAJM/UncaughtExceptionHook/uncaught_logger.py
EasyLoggerAJM/backend/__init__.py
EasyLoggerAJM/backend/easy_logger_initializer.py
EasyLoggerAJM/backend/errs.py
EasyLoggerAJM/backend/sub_initializers.py
EasyLoggerAJM/logger_parts/__init__.py
EasyLoggerAJM/logger_parts/filters.py
EasyLoggerAJM/logger_parts/formatters.py
EasyLoggerAJM/logger_parts/handlers.py
easyloggerajm-1.9.7.dist-info/licenses/LICENSE.txt
easyloggerajm-1.9.7.dist-info/METADATA
easyloggerajm-1.9.7.dist-info/WHEEL
easyloggerajm-1.9.7.dist-info/top_level.txt
easyloggerajm-1.9.7.dist-info/RECORD
