Metadata-Version: 2.4
Name: EasyLoggerAJM
Version: 1.9.7
Summary: logger with already set up generalized file handlers
Home-page: https://github.com/amcsparron2793-Water/EasyLoggerAJM
Download-URL: https://github.com/amcsparron2793-Water/EasyLoggerAJM/archive/refs/tags/1.9.7.tar.gz
Author: Amcsparron
Author-email: amcsparron@albanyny.gov
License: MIT License
Keywords: logging
License-File: LICENSE.txt
Requires-Dist: ColorizerAJM
Dynamic: author
Dynamic: author-email
Dynamic: download-url
Dynamic: home-page
Dynamic: keywords
Dynamic: license
Dynamic: license-file
Dynamic: requires-dist
Dynamic: summary
